{
  "products": [
    {
      "id": "1",
      "name": "Laptop HP Pavilion",
      "type": "Informatique",
      "price": 1200,
      "barcode": "1234567890123",
      "stocks": [
        {
          "id": 1999,
          "quantity": 216
        }
      ],
      "editedBy": [
        {
          "warehousemanId": 1,
          "at": "2025-02-14"
        }
      ]
    },
    {
      "id": "2",
      "name": "Azerty",
      "type": "Accessoires",
      "price": 100,
      "barcode": "9876543210987",
      "stocks": [
        {
          "id": 1999,
          "quantity": 20
        }
      ],
      "editedBy": [
        {
          "warehousemanId": "1333",
          "at": "2025-02-17"
        }
      ]
    },
    {
      "id": "3",
      "name": "Pc Gamer Omen By HP",
      "type": "Informatique",
      "barcode": "1236543210987",
      "price": 11000,
      "supplier": "HP",
      "image": "https://technoplace.ma/11482-large_default/hp-omen-17-i7-7700hq-173-16gb-2tb-geforce-gtx-10.jpg",
      "stocks": [],
      "editedBy": [
        {
          "warehousemanId": 1444,
          "at": "2025-02-02"
        }
      ]
    },
    {
      "id": "b8e0",
      "name": "Gsgsggsg",
      "type": "Shhsggsgv",
      "barcode": "12678",
      "price": 84884,
      "supplier": "Gsgsg",
      "image": "",
      "stocks": [
        {
          "id": 1739565137852,
          "name": "Uwhgegveh",
          "quantity": 545,
          "localisation": {
            "city": "Aggwgwgg",
            "latitude": 645,
            "longitude": 64
          }
        }
      ],
      "editedBy": [
        {
          "warehousemanId": 1333,
          "at": "2025-02-14"
        },
        {
          "warehousemanId": 1333,
          "at": "2025-02-14"
        }
      ]
    },
    {
      "id": "6076",
      "name": "Gsgsggsg",
      "type": "Shhsggsgv",
      "barcode": "12678",
      "price": 84884,
      "supplier": "Gsgsg",
      "image": "",
      "stocks": [],
      "editedBy": [
        {
          "warehousemanId": 1333,
          "at": "2025-02-14"
        }
      ]
    },
    {
      "id": "20e4",
      "name": "Moga",
      "type": "Hsgwg",
      "price": 646,
      "supplier": "Ggwgw",
      "image": "",
      "stocks": [
        {
          "id": 1739735171524,
          "name": "Moga",
          "quantity": 4648,
          "localisation": {
            "city": "Gssg",
            "latitude": 45,
            "longitude": 64
          }
        }
      ],
      "editedBy": [
        {
          "warehousemanId": "1333",
          "at": "2025-02-16"
        },
        {
          "warehousemanId": "1333",
          "at": "2025-02-16"
        }
      ]
    },
    {
      "id": "8d1d",
      "name": "Hysuue",
      "type": "Yssyd7",
      "barcode": "586",
      "price": 68,
      "supplier": "Yssys",
      "image": "",
      "stocks": [],
      "editedBy": [
        {
          "warehousemanId": "1333",
          "at": "2025-02-17"
        }
      ]
    }
  ],
  "warehousemans": [
    {
      "id": "1333",
      "name": "Amine Boutaleb",
      "dob": "1988-05-02",
      "city": "Oujda",
      "secretKey": "AH90907J",
      "warehouseId": 1999
    },
    {
      "id": "1444",
      "name": "Karim El Mansouri",
      "dob": "1990-09-15",
      "city": "Marrakesh",
      "secretKey": "RK189987A",
      "warehouseId": 2991
    }
  ],
  "statistics": {
    "totalProducts": 7,
    "outOfStock": 1,
    "totalStockValue": 70,
    "mostAddedProducts": [
      {
        "product": {
          "id": "b8e0",
          "name": "Gsgsggsg",
          "price": 84884
        },
        "quantity": 0,
        "date": "2025-02-14T20:32:00.764Z"
      },
      {
        "product": {
          "id": "6076",
          "name": "Gsgsggsg",
          "price": 84884
        },
        "quantity": 0,
        "date": "2025-02-14T20:48:23.705Z"
      },
      {
        "product": {
          "id": "20e4",
          "name": "Moga",
          "price": 646
        },
        "quantity": 0,
        "date": "2025-02-16T19:45:56.891Z"
      },
      {
        "product": {
          "id": "8d1d",
          "name": "Hysuue",
          "price": 68
        },
        "quantity": 0,
        "date": "2025-02-17T08:28:21.196Z"
      }
    ],
    "mostRemovedProducts": []
  }
}